influxdb_querier/__init__.py
influxdb_querier/clauses.py
influxdb_querier/client.py
influxdb_querier/compiler.py
influxdb_querier/functions.py
influxdb_querier/query.py
influxdb_querier/tag.py
influxdb_querier/tag_operator.py
influxdb_querier-1.3.0.dist-info/LICENSE
influxdb_querier-1.3.0.dist-info/METADATA
influxdb_querier-1.3.0.dist-info/WHEEL
influxdb_querier-1.3.0.dist-info/top_level.txt
influxdb_querier-1.3.0.dist-info/RECORD
